schedulorium/__init__.py
schedulorium/timetabling.py
schedulorium-1.0.0.dist-info/LICENSE
schedulorium-1.0.0.dist-info/METADATA
schedulorium-1.0.0.dist-info/WHEEL
schedulorium-1.0.0.dist-info/top_level.txt
schedulorium-1.0.0.dist-info/RECORD
