Metadata-Version: 2.1
Name: schedulorium
Version: 1.0.0
Summary: A small package to create a timetable using integer programming
Author: Roberto Schinina
Author-email: roberto.schinina02@gmail.com
Classifier: License :: OSI Approved :: MIT License
Classifier: Programming Language :: Python :: 3.12
Classifier: Operating System :: OS Independent
Requires-Python: >=3.12
License-File: LICENSE
Requires-Dist: numpy
Requires-Dist: pandas
Requires-Dist: matplotlib
Requires-Dist: amplpy
Requires-Dist: openpyxl
